[{"name":"Kolja","age":40},{"name":"Katja","age":18},{"name":"Masha","age":45},{"name":"Anna","age":42},{"name":"Sveta","age":35},{"name":"Katja","age":22},{"name":"Sveta","age":29},{"name":"Sveta","age":44},{"name":"Sveta","age":44},{"name":"Sveta","age":38},{"name":"Sveta","age":37},{"name":"Katja","age":19},{"name":"Anna","age":31},{"name":"Katja","age":28},{"name":"Sveta","age":34},{"name":"Masha","age":24},{"name":"Sveta","age":21},{"name":"Kolja","age":24},{"name":"Masha","age":33},{"name":"Sveta","age":19},{"name":"Masha","age":34},{"name":"Sveta","age":24},{"name":"Anna","age":26},{"name":"Sveta","age":22},{"name":"Kolja","age":24},{"name":"Masha","age":25},{"name":"Sveta","age":28},{"name":"Kolja","age":31},{"name":"Masha","age":43},{"name":"Masha","age":33},{"name":"Sveta","age":35},{"name":"Anna","age":38},{"name":"Anna","age":32},{"name":"Kolja","age":22},{"name":"Kolja","age":24},{"name":"Anna","age":31},{"name":"Kolja","age":39},{"name":"Masha","age":32},{"name":"Masha","age":40},{"name":"Kolja","age":33},{"name":"Kolja","age":32},{"name":"Katja","age":28},{"name":"Katja","age":26},{"name":"Anna","age":38},{"name":"Masha","age":28},{"name":"Kolja","age":18},{"name":"Masha","age":32},{"name":"Masha","age":30},{"name":"Sveta","age":35},{"name":"Kolja","age":28}]